{"width":1024,"imagePath":"EquipEffects_tex.png","height":256,"name":"EquipEffects","SubTexture":[{"width":658,"y":1,"height":245,"name":"EquipEffects/SquareBG","x":1},{"width":13,"y":128,"height":13,"name":"EquipEffects/Light1","x":991},{"width":13,"y":128,"height":13,"name":"EquipEffects/Light2","x":1006},{"width":13,"y":113,"height":13,"name":"EquipEffects/Light3","x":1006},{"width":13,"y":113,"height":13,"name":"EquipEffects/Light4","x":991},{"width":162,"y":1,"height":110,"name":"EquipEffects/LightLine1","x":854},{"frameY":0,"y":113,"frameWidth":162,"frameX":0,"frameHeight":110,"width":135,"height":101,"name":"EquipEffects/LightLine2","x":854},{"width":191,"y":1,"height":190,"name":"EquipEffects/UI_item_EquipFrame","x":661}]}